test_project_ci_cd/__init__.py
test_project_ci_cd/__main__.py
test_project_ci_cd/calc.py
test_project_ci_cd/py.typed
test_project_ci_cd-0.7.19.dist-info/METADATA
test_project_ci_cd-0.7.19.dist-info/WHEEL
test_project_ci_cd-0.7.19.dist-info/entry_points.txt
test_project_ci_cd-0.7.19.dist-info/RECORD
